guido/__init__.py
guido/data/PAM_scores.pkl
guido/data/V3_model_full.pickle
guido/data/V3_model_nopos.pickle
guido/data/mismatch_score.pkl
guido/genome.py
guido/guides.py
guido/helpers.py
guido/locus.py
guido/mmej.py
guido/off_targets.py
guido/templates/guide_details.j2
guido-0.1.5.dist-info/LICENSE
guido-0.1.5.dist-info/WHEEL
guido-0.1.5.dist-info/METADATA
guido-0.1.5.dist-info/RECORD
