Metadata-Version: 2.1
Name: guido
Version: 0.1.5
Summary: 
Author: Nace Kranjc
Author-email: nace.kranjc@gmail.com
Requires-Python: >3.9,<=3.10
Classifier: Programming Language :: Python :: 3
Classifier: Programming Language :: Python :: 3.10
Requires-Dist: Jinja2 (>=3.0.1,<4.0.0)
Requires-Dist: h5py (>=3.3.0,<4.0.0)
Requires-Dist: mcdm (>=1.4,<2.0)
Requires-Dist: ncls (>=0.0.60,<0.0.61)
Requires-Dist: numpy (>=1.21.1,<2.0.0)
Requires-Dist: pandas (>=1.3.1,<2.0.0)
Requires-Dist: pyfaidx (>=0.6.1,<0.7.0)
Requires-Dist: pyranges (>=0.0.101,<0.0.102)
Requires-Dist: scikit-allel (>=1.3.5,<2.0.0)
Requires-Dist: zarr (>=2.8.3,<3.0.0)
